{"cameraMode":{"drawMode":0,"name":"Shaded","section":"Shading Mode"},"sceneLighting":false,"audioPlay":false,"sceneViewState":{"m_AlwaysRefresh":false,"showFog":true,"showSkybox":false,"showFlares":true,"showImageEffects":true,"showParticleSystems":true,"showVisualEffectGraphs":true,"m_FxEnabled":true},"in2DMode":false,"pivot":{"x":-5.0,"y":0.3999999761581421,"z":0.4999997615814209},"rotation":{"x":0.2868898808956146,"y":-0.011495414189994336,"z":0.0034426567144691946,"w":0.9578860402107239},"size":2.165066719055176,"orthographic":false}